{
  "id": "chapters/applications/real-world-deployment",
  "title": "Lesson 5.1: Real-World Deployment Challenges",
  "description": "Transferring from simulation to reality, handling uncertainty, and robustness in real-world applications",
  "source": "@site/docs/chapters/05-applications/01-real-world-deployment.mdx",
  "sourceDirName": "chapters/05-applications",
  "slug": "/chapters/applications/real-world-deployment",
  "permalink": "/docs/chapters/applications/real-world-deployment",
  "draft": false,
  "unlisted": false,
  "editUrl": "https://github.com/facebook/docusaurus/tree/main/packages/create-docusaurus/templates/shared/docs/chapters/05-applications/01-real-world-deployment.mdx",
  "tags": [],
  "version": "current",
  "sidebarPosition": 1,
  "frontMatter": {
    "title": "Lesson 5.1: Real-World Deployment Challenges",
    "sidebar_label": "Real-World Deployment Challenges",
    "description": "Transferring from simulation to reality, handling uncertainty, and robustness in real-world applications",
    "keywords": [
      "real-world deployment",
      "simulation-to-reality",
      "robustness",
      "uncertainty handling"
    ]
  },
  "sidebar": "docsSidebar",
  "previous": {
    "title": "Autonomous Learning and Adaptation",
    "permalink": "/docs/chapters/intelligence/autonomous-learning"
  },
  "next": {
    "title": "Real-World Deployment Challenges",
    "permalink": "/docs/chapters/applications/real-world-deployment"
  }
}